[{"model": "generic_name.genericname", "pk": "acarbose", "fields": {}}, {"model": "generic_name.genericname", "pk": "acetazolamide", "fields": {}}, {"model": "generic_name.genericname", "pk": "acyclovir", "fields": {}}, {"model": "generic_name.genericname", "pk": "aggrenox", "fields": {}}, {"model": "generic_name.genericname", "pk": "albendazole", "fields": {}}, {"model": "generic_name.genericname", "pk": "albuterol", "fields": {}}, {"model": "generic_name.genericname", "pk": "alendronate", "fields": {}}, {"model": "generic_name.genericname", "pk": "alfuzosin", "fields": {}}, {"model": "generic_name.genericname", "pk": "allopurinol", "fields": {}}, {"model": "generic_name.genericname", "pk": "amiloride_hydrochlorothiazide", "fields": {}}, {"model": "generic_name.genericname", "pk": "amiodarone", "fields": {}}, {"model": "generic_name.genericname", "pk": "amitriptyline", "fields": {}}, {"model": "generic_name.genericname", "pk": "amlodipine", "fields": {}}, {"model": "generic_name.genericname", "pk": "amoxicillin", "fields": {}}, {"model": "generic_name.genericname", "pk": "anastrozole", "fields": {}}, {"model": "generic_name.genericname", "pk": "aripiprazole", "fields": {}}, {"model": "generic_name.genericname", "pk": "atenolol", "fields": {}}, {"model": "generic_name.genericname", "pk": "atomoxetine", "fields": {}}, {"model": "generic_name.genericname", "pk": "atorvastatin", "fields": {}}, {"model": "generic_name.genericname", "pk": "azathioprine", "fields": {}}, {"model": "generic_name.genericname", "pk": "azithromycin", "fields": {}}, {"model": "generic_name.genericname", "pk": "baclofen", "fields": {}}, {"model": "generic_name.genericname", "pk": "benazepril", "fields": {}}, {"model": "generic_name.genericname", "pk": "benzoyl_peroxide", "fields": {}}, {"model": "generic_name.genericname", "pk": "biaxin", "fields": {}}, {"model": "generic_name.genericname", "pk": "bicalutamide", "fields": {}}, {"model": "generic_name.genericname", "pk": "bisoprolol", "fields": {}}, {"model": "generic_name.genericname", "pk": "bromocriptine", "fields": {}}, {"model": "generic_name.genericname", "pk": "bupropion", "fields": {}}, {"model": "generic_name.genericname", "pk": "buspirone", "fields": {}}, {"model": "generic_name.genericname", "pk": "cabergoline", "fields": {}}, {"model": "generic_name.genericname", "pk": "calcitriol", "fields": {}}, {"model": "generic_name.genericname", "pk": "candesartan", "fields": {}}, {"model": "generic_name.genericname", "pk": "captopril", "fields": {}}, {"model": "generic_name.genericname", "pk": "carbamazepine", "fields": {}}, {"model": "generic_name.genericname", "pk": "carbidopa_levodopa", "fields": {}}, {"model": "generic_name.genericname", "pk": "carvedilol", "fields": {}}, {"model": "generic_name.genericname", "pk": "cefdinir", "fields": {}}, {"model": "generic_name.genericname", "pk": "cefixime", "fields": {}}, {"model": "generic_name.genericname", "pk": "cefpodoxime", "fields": {}}, {"model": "generic_name.genericname", "pk": "cefuroxime", "fields": {}}, {"model": "generic_name.genericname", "pk": "celecoxib", "fields": {}}, {"model": "generic_name.genericname", "pk": "cephalexin", "fields": {}}, {"model": "generic_name.genericname", "pk": "cetirizine", "fields": {}}, {"model": "generic_name.genericname", "pk": "chloramphenicol", "fields": {}}, {"model": "generic_name.genericname", "pk": "chloroquine", "fields": {}}, {"model": "generic_name.genericname", "pk": "cilostazol", "fields": {}}, {"model": "generic_name.genericname", "pk": "ciprofloxacin", "fields": {}}, {"model": "generic_name.genericname", "pk": "citalopram", "fields": {}}, {"model": "generic_name.genericname", "pk": "clarithromycin", "fields": {}}, {"model": "generic_name.genericname", "pk": "clavulanate", "fields": {}}, {"model": "generic_name.genericname", "pk": "clindamycin", "fields": {}}, {"model": "generic_name.genericname", "pk": "clomiphene", "fields": {}}, {"model": "generic_name.genericname", "pk": "clomipramine", "fields": {}}, {"model": "generic_name.genericname", "pk": "clonidine", "fields": {}}, {"model": "generic_name.genericname", "pk": "clopidogrel", "fields": {}}, {"model": "generic_name.genericname", "pk": "clozapine", "fields": {}}, {"model": "generic_name.genericname", "pk": "conjugated_estrogens", "fields": {}}, {"model": "generic_name.genericname", "pk": "cyclophosphamide", "fields": {}}, {"model": "generic_name.genericname", "pk": "cyproheptadine", "fields": {}}, {"model": "generic_name.genericname", "pk": "danazol", "fields": {}}, {"model": "generic_name.genericname", "pk": "desogestrel", "fields": {}}, {"model": "generic_name.genericname", "pk": "dexamethasone", "fields": {}}, {"model": "generic_name.genericname", "pk": "diclofenac", "fields": {}}, {"model": "generic_name.genericname", "pk": "digoxin", "fields": {}}, {"model": "generic_name.genericname", "pk": "diltiazem", "fields": {}}, {"model": "generic_name.genericname", "pk": "disulfiram", "fields": {}}, {"model": "generic_name.genericname", "pk": "divalproex", "fields": {}}, {"model": "generic_name.genericname", "pk": "donepezil", "fields": {}}, {"model": "generic_name.genericname", "pk": "doryx", "fields": {}}, {"model": "generic_name.genericname", "pk": "doxazosin", "fields": {}}, {"model": "generic_name.genericname", "pk": "doxepin", "fields": {}}, {"model": "generic_name.genericname", "pk": "duloxetine", "fields": {}}, {"model": "generic_name.genericname", "pk": "dutasteride", "fields": {}}, {"model": "generic_name.genericname", "pk": "emycin", "fields": {}}, {"model": "generic_name.genericname", "pk": "enalapril", "fields": {}}, {"model": "generic_name.genericname", "pk": "ergotamine_caffeine", "fields": {}}, {"model": "generic_name.genericname", "pk": "eryc", "fields": {}}, {"model": "generic_name.genericname", "pk": "escitalopram", "fields": {}}, {"model": "generic_name.genericname", "pk": "esidrix", "fields": {}}, {"model": "generic_name.genericname", "pk": "eskalith", "fields": {}}, {"model": "generic_name.genericname", "pk": "esomeprazole", "fields": {}}, {"model": "generic_name.genericname", "pk": "estradiol", "fields": {}}, {"model": "generic_name.genericname", "pk": "ethambutol", "fields": {}}, {"model": "generic_name.genericname", "pk": "ethinyl_estradiol", "fields": {}}, {"model": "generic_name.genericname", "pk": "ethinylestradiol", "fields": {}}, {"model": "generic_name.genericname", "pk": "ezetimibe", "fields": {}}, {"model": "generic_name.genericname", "pk": "ezetimibe_simvastatin", "fields": {}}, {"model": "generic_name.genericname", "pk": "famciclovir", "fields": {}}, {"model": "generic_name.genericname", "pk": "felodipine", "fields": {}}, {"model": "generic_name.genericname", "pk": "femcare", "fields": {}}, {"model": "generic_name.genericname", "pk": "fenofibrate", "fields": {}}, {"model": "generic_name.genericname", "pk": "fexofenadine", "fields": {}}, {"model": "generic_name.genericname", "pk": "finasteride", "fields": {}}, {"model": "generic_name.genericname", "pk": "flavoxate", "fields": {}}, {"model": "generic_name.genericname", "pk": "fluconazole", "fields": {}}, {"model": "generic_name.genericname", "pk": "flutamide", "fields": {}}, {"model": "generic_name.genericname", "pk": "fluticasone_salmeterol", "fields": {}}, {"model": "generic_name.genericname", "pk": "fluvoxamine", "fields": {}}, {"model": "generic_name.genericname", "pk": "furosemide", "fields": {}}, {"model": "generic_name.genericname", "pk": "gabapentin", "fields": {}}, {"model": "generic_name.genericname", "pk": "gemfibrozil", "fields": {}}, {"model": "generic_name.genericname", "pk": "glimepiride", "fields": {}}, {"model": "generic_name.genericname", "pk": "glipizide", "fields": {}}, {"model": "generic_name.genericname", "pk": "glyburide", "fields": {}}, {"model": "generic_name.genericname", "pk": "granisetron", "fields": {}}, {"model": "generic_name.genericname", "pk": "griseofulvin", "fields": {}}, {"model": "generic_name.genericname", "pk": "hydrodiuril", "fields": {}}, {"model": "generic_name.genericname", "pk": "hydroxyurea", "fields": {}}, {"model": "generic_name.genericname", "pk": "hydroxyzine", "fields": {}}, {"model": "generic_name.genericname", "pk": "ibuprofen", "fields": {}}, {"model": "generic_name.genericname", "pk": "indapamide", "fields": {}}, {"model": "generic_name.genericname", "pk": "indinavir", "fields": {}}, {"model": "generic_name.genericname", "pk": "indomethacin", "fields": {}}, {"model": "generic_name.genericname", "pk": "ipratropium", "fields": {}}, {"model": "generic_name.genericname", "pk": "irbesartan", "fields": {}}, {"model": "generic_name.genericname", "pk": "isotretinoin", "fields": {}}, {"model": "generic_name.genericname", "pk": "ivermectin", "fields": {}}, {"model": "generic_name.genericname", "pk": "ketoconazole", "fields": {}}, {"model": "generic_name.genericname", "pk": "labetalol", "fields": {}}, {"model": "generic_name.genericname", "pk": "lamictal", "fields": {}}, {"model": "generic_name.genericname", "pk": "lamivudine", "fields": {}}, {"model": "generic_name.genericname", "pk": "lamotrigine", "fields": {}}, {"model": "generic_name.genericname", "pk": "lansoprazole", "fields": {}}, {"model": "generic_name.genericname", "pk": "leflunomide", "fields": {}}, {"model": "generic_name.genericname", "pk": "letrozole", "fields": {}}, {"model": "generic_name.genericname", "pk": "levofloxacin", "fields": {}}, {"model": "generic_name.genericname", "pk": "levonorgestrel_ethinyl", "fields": {}}, {"model": "generic_name.genericname", "pk": "levothyroxine", "fields": {}}, {"model": "generic_name.genericname", "pk": "linezolid", "fields": {}}, {"model": "generic_name.genericname", "pk": "lisinopril_hydrochlorothiazide", "fields": {}}, {"model": "generic_name.genericname", "pk": "lithobid", "fields": {}}, {"model": "generic_name.genericname", "pk": "loratadine", "fields": {}}, {"model": "generic_name.genericname", "pk": "losartan", "fields": {}}, {"model": "generic_name.genericname", "pk": "macrodantin", "fields": {}}, {"model": "generic_name.genericname", "pk": "mebendazole", "fields": {}}, {"model": "generic_name.genericname", "pk": "mebeverine", "fields": {}}, {"model": "generic_name.genericname", "pk": "medroxyprogesterone", "fields": {}}, {"model": "generic_name.genericname", "pk": "mefenamic_acid", "fields": {}}, {"model": "generic_name.genericname", "pk": "mefloquine", "fields": {}}, {"model": "generic_name.genericname", "pk": "meloxicam", "fields": {}}, {"model": "generic_name.genericname", "pk": "mesalamine", "fields": {}}, {"model": "generic_name.genericname", "pk": "metformin", "fields": {}}, {"model": "generic_name.genericname", "pk": "methocarbamol", "fields": {}}, {"model": "generic_name.genericname", "pk": "metoclopramide", "fields": {}}, {"model": "generic_name.genericname", "pk": "metoprolol", "fields": {}}, {"model": "generic_name.genericname", "pk": "metronidazole", "fields": {}}, {"model": "generic_name.genericname", "pk": "microzide", "fields": {}}, {"model": "generic_name.genericname", "pk": "minocycline", "fields": {}}, {"model": "generic_name.genericname", "pk": "mirtazapine", "fields": {}}, {"model": "generic_name.genericname", "pk": "misoprostol", "fields": {}}, {"model": "generic_name.genericname", "pk": "monopril", "fields": {}}, {"model": "generic_name.genericname", "pk": "montelukast", "fields": {}}, {"model": "generic_name.genericname", "pk": "nabumetone", "fields": {}}, {"model": "generic_name.genericname", "pk": "naltrexone", "fields": {}}, {"model": "generic_name.genericname", "pk": "naproxen", "fields": {}}, {"model": "generic_name.genericname", "pk": "nateglinide", "fields": {}}, {"model": "generic_name.genericname", "pk": "nebivolol", "fields": {}}, {"model": "generic_name.genericname", "pk": "nifedipine", "fields": {}}, {"model": "generic_name.genericname", "pk": "nimodipine", "fields": {}}, {"model": "generic_name.genericname", "pk": "nitrofurantoin", "fields": {}}, {"model": "generic_name.genericname", "pk": "norethindrone", "fields": {}}, {"model": "generic_name.genericname", "pk": "norfloxacin", "fields": {}}, {"model": "generic_name.genericname", "pk": "nortriptyline", "fields": {}}, {"model": "generic_name.genericname", "pk": "ofloxacin", "fields": {}}, {"model": "generic_name.genericname", "pk": "olanzapine", "fields": {}}, {"model": "generic_name.genericname", "pk": "omeprazole", "fields": {}}, {"model": "generic_name.genericname", "pk": "ondansetron", "fields": {}}, {"model": "generic_name.genericname", "pk": "oretic", "fields": {}}, {"model": "generic_name.genericname", "pk": "orlistat", "fields": {}}, {"model": "generic_name.genericname", "pk": "ortho", "fields": {}}, {"model": "generic_name.genericname", "pk": "oxcarbazepine", "fields": {}}, {"model": "generic_name.genericname", "pk": "oxybutynin", "fields": {}}, {"model": "generic_name.genericname", "pk": "pantoprazole", "fields": {}}, {"model": "generic_name.genericname", "pk": "paroxetine", "fields": {}}, {"model": "generic_name.genericname", "pk": "pentoxifylline", "fields": {}}, {"model": "generic_name.genericname", "pk": "perindopril_erbumine", "fields": {}}, {"model": "generic_name.genericname", "pk": "periostat", "fields": {}}, {"model": "generic_name.genericname", "pk": "phenazopyridine", "fields": {}}, {"model": "generic_name.genericname", "pk": "phenytoin", "fields": {}}, {"model": "generic_name.genericname", "pk": "pioglitazone", "fields": {}}, {"model": "generic_name.genericname", "pk": "pioglitazone_metformin", "fields": {}}, {"model": "generic_name.genericname", "pk": "piroxicam", "fields": {}}, {"model": "generic_name.genericname", "pk": "prazosin", "fields": {}}, {"model": "generic_name.genericname", "pk": "prednisone", "fields": {}}, {"model": "generic_name.genericname", "pk": "probenecid", "fields": {}}, {"model": "generic_name.genericname", "pk": "prochlorperazine", "fields": {}}, {"model": "generic_name.genericname", "pk": "propranolol", "fields": {}}, {"model": "generic_name.genericname", "pk": "pyridostigmine", "fields": {}}, {"model": "generic_name.genericname", "pk": "quetiapine", "fields": {}}, {"model": "generic_name.genericname", "pk": "rabeprazole", "fields": {}}, {"model": "generic_name.genericname", "pk": "raloxifene", "fields": {}}, {"model": "generic_name.genericname", "pk": "ramipril", "fields": {}}, {"model": "generic_name.genericname", "pk": "ranitidine", "fields": {}}, {"model": "generic_name.genericname", "pk": "repaglinide", "fields": {}}, {"model": "generic_name.genericname", "pk": "risedronate_sodium", "fields": {}}, {"model": "generic_name.genericname", "pk": "risperidone", "fields": {}}, {"model": "generic_name.genericname", "pk": "rivastigmine", "fields": {}}, {"model": "generic_name.genericname", "pk": "rizatriptan", "fields": {}}, {"model": "generic_name.genericname", "pk": "ropinirole", "fields": {}}, {"model": "generic_name.genericname", "pk": "rosiglitazone", "fields": {}}, {"model": "generic_name.genericname", "pk": "selegiline", "fields": {}}, {"model": "generic_name.genericname", "pk": "serophene", "fields": {}}, {"model": "generic_name.genericname", "pk": "sevelamer", "fields": {}}, {"model": "generic_name.genericname", "pk": "sildenafil", "fields": {}}, {"model": "generic_name.genericname", "pk": "simvastatin", "fields": {}}, {"model": "generic_name.genericname", "pk": "sotalol", "fields": {}}, {"model": "generic_name.genericname", "pk": "spironolactone", "fields": {}}, {"model": "generic_name.genericname", "pk": "stavudine", "fields": {}}, {"model": "generic_name.genericname", "pk": "sulfamethoxazole_trimethoprim", "fields": {}}, {"model": "generic_name.genericname", "pk": "sulfasalazine", "fields": {}}, {"model": "generic_name.genericname", "pk": "sumatriptan", "fields": {}}, {"model": "generic_name.genericname", "pk": "tacrolimus", "fields": {}}, {"model": "generic_name.genericname", "pk": "tadalafil", "fields": {}}, {"model": "generic_name.genericname", "pk": "tamoxifen", "fields": {}}, {"model": "generic_name.genericname", "pk": "tamsulosin", "fields": {}}, {"model": "generic_name.genericname", "pk": "telmisartan", "fields": {}}, {"model": "generic_name.genericname", "pk": "terazosin", "fields": {}}, {"model": "generic_name.genericname", "pk": "terbinafine", "fields": {}}, {"model": "generic_name.genericname", "pk": "tetracycline", "fields": {}}, {"model": "generic_name.genericname", "pk": "tizanidine", "fields": {}}, {"model": "generic_name.genericname", "pk": "tolterodine", "fields": {}}, {"model": "generic_name.genericname", "pk": "topiramate", "fields": {}}, {"model": "generic_name.genericname", "pk": "torsemide", "fields": {}}, {"model": "generic_name.genericname", "pk": "tranexamic_acid", "fields": {}}, {"model": "generic_name.genericname", "pk": "trazodone", "fields": {}}, {"model": "generic_name.genericname", "pk": "triamcinolone", "fields": {}}, {"model": "generic_name.genericname", "pk": "trihexyphenidyl", "fields": {}}, {"model": "generic_name.genericname", "pk": "valacyclovir", "fields": {}}, {"model": "generic_name.genericname", "pk": "valsartan", "fields": {}}, {"model": "generic_name.genericname", "pk": "vardenafil", "fields": {}}, {"model": "generic_name.genericname", "pk": "vaseretic", "fields": {}}, {"model": "generic_name.genericname", "pk": "venlafaxine", "fields": {}}, {"model": "generic_name.genericname", "pk": "verapamil", "fields": {}}, {"model": "generic_name.genericname", "pk": "warfarin", "fields": {}}]